nlp_datasets/__init__.py
nlp_datasets/dataset.py
nlp_datasets/seq2seq/__init__.py
nlp_datasets/seq2seq/seq2seq_dataset.py
nlp_datasets/seq2seq/seq2seq_dataset_test.py
nlp_datasets/seq_classify/__init__.py
nlp_datasets/seq_classify/seq_classify_dataset.py
nlp_datasets/seq_classify/seq_classify_dataset_test.py
nlp_datasets/seq_match/__init__.py
nlp_datasets/seq_match/seq_match_dataset.py
nlp_datasets/seq_match/seq_match_dataset_test.py
nlp_datasets/tokenizers/__init__.py
nlp_datasets/tokenizers/abstract_tokenizer.py
nlp_datasets/tokenizers/space_tokenizer.py
nlp_datasets/tokenizers/space_tokenizer_test.py
nlp_datasets/tokenizers/token_filter.py
nlp_datasets/utils/__init__.py
nlp_datasets/utils/data_dir_utils.py
nlp_datasets-1.3.0.dist-info/LICENSE
nlp_datasets-1.3.0.dist-info/METADATA
nlp_datasets-1.3.0.dist-info/WHEEL
nlp_datasets-1.3.0.dist-info/top_level.txt
nlp_datasets-1.3.0.dist-info/RECORD
