Metadata-Version: 2.1
Name: nlp-datasets
Version: 1.3.0
Summary: A dataset utils repository based on tf.data. For tensorflow 2.x only!
Home-page: https://github.com/luozhouyang/nlp-datasets
Author: ZhouYang Luo
Author-email: zhouyang.luo@gmail.com
License: MIT License
Platform: UNKNOWN
Classifier: Programming Language :: Python :: 3.6
Classifier: License :: OSI Approved :: MIT License
Classifier: Operating System :: OS Independent
